coverity_mcp/__init__.py
coverity_mcp/__main__.py
coverity_mcp/main.py
coverity_mcp-0.1.1.dist-info/METADATA
coverity_mcp-0.1.1.dist-info/WHEEL
coverity_mcp-0.1.1.dist-info/entry_points.txt
coverity_mcp-0.1.1.dist-info/RECORD
