Metadata-Version: 2.4
Name: coverity-mcp
Version: 0.1.1
Summary: MCP server for Blackduck Coverity
Requires-Python: >=3.13
Requires-Dist: mcp>=1.10.1
Requires-Dist: requests>=2.32.4
